{
  "generatedBy": "electron/scripts/generate-system-map.js",
  "counts": {
    "apiRoutes": 100,
    "ipcHandlers": 160,
    "preloadBridges": 152,
    "dashboardPages": 14,
    "capabilityContracts": 5
  },
  "apiRoutes": [
    {
      "path": "/api/auth/token",
      "sources": [
        "electron/lib/cron-api.js"
      ],
      "kinds": [
        "local-api"
      ]
    },
    {
      "path": "/api/brand-assets/list",
      "sources": [
        "electron/lib/cron-api.js"
      ],
      "kinds": [
        "local-api"
      ]
    },
    {
      "path": "/api/brand-assets/save",
      "sources": [
        "electron/lib/cron-api.js"
      ],
      "kinds": [
        "local-api"
      ]
    },
    {
      "path": "/api/capabilities",
      "sources": [
        "electron/lib/cron-api.js"
      ],
      "kinds": [
        "local-api"
      ]
    },
    {
      "path": "/api/ceo-rules/write",
      "sources": [
        "electron/lib/cron-api.js"
      ],
      "kinds": [
        "local-api"
      ]
    },
    {
      "path": "/api/cron/create",
      "sources": [
        "electron/lib/cron-api.js"
      ],
      "kinds": [
        "local-api"
      ]
    },
    {
      "path": "/api/cron/delete",
      "sources": [
        "electron/lib/cron-api.js"
      ],
      "kinds": [
        "local-api"
      ]
    },
    {
      "path": "/api/cron/list",
      "sources": [
        "electron/lib/cron-api.js"
      ],
      "kinds": [
        "local-api"
      ]
    },
    {
      "path": "/api/cron/replace",
      "sources": [
        "electron/lib/cron-api.js"
      ],
      "kinds": [
        "local-api"
      ]
    },
    {
      "path": "/api/cron/toggle",
      "sources": [
        "electron/lib/cron-api.js"
      ],
      "kinds": [
        "local-api"
      ]
    },
    {
      "path": "/api/customer-memory/write",
      "sources": [
        "electron/lib/cron-api.js"
      ],
      "kinds": [
        "local-api"
      ]
    },
    {
      "path": "/api/exec",
      "sources": [
        "electron/lib/cron-api.js"
      ],
      "kinds": [
        "local-api"
      ]
    },
    {
      "path": "/api/fb/post",
      "sources": [
        "electron/lib/cron-api.js"
      ],
      "kinds": [
        "local-api"
      ]
    },
    {
      "path": "/api/fb/recent",
      "sources": [
        "electron/lib/cron-api.js"
      ],
      "kinds": [
        "local-api"
      ]
    },
    {
      "path": "/api/fb/schedule",
      "sources": [
        "electron/lib/cron-api.js"
      ],
      "kinds": [
        "local-api"
      ]
    },
    {
      "path": "/api/fb/schedule/approve",
      "sources": [
        "electron/lib/fb-schedule.js"
      ],
      "kinds": [
        "fb-schedule-api"
      ]
    },
    {
      "path": "/api/fb/schedule/create",
      "sources": [
        "electron/lib/fb-schedule.js"
      ],
      "kinds": [
        "fb-schedule-api"
      ]
    },
    {
      "path": "/api/fb/schedule/delete",
      "sources": [
        "electron/lib/fb-schedule.js"
      ],
      "kinds": [
        "fb-schedule-api"
      ]
    },
    {
      "path": "/api/fb/schedule/edit-caption",
      "sources": [
        "electron/lib/fb-schedule.js"
      ],
      "kinds": [
        "fb-schedule-api"
      ]
    },
    {
      "path": "/api/fb/schedule/list",
      "sources": [
        "electron/lib/fb-schedule.js"
      ],
      "kinds": [
        "fb-schedule-api"
      ]
    },
    {
      "path": "/api/fb/schedule/pending",
      "sources": [
        "electron/lib/fb-schedule.js"
      ],
      "kinds": [
        "fb-schedule-api"
      ]
    },
    {
      "path": "/api/fb/schedule/regenerate",
      "sources": [
        "electron/lib/fb-schedule.js"
      ],
      "kinds": [
        "fb-schedule-api"
      ]
    },
    {
      "path": "/api/fb/schedule/reject",
      "sources": [
        "electron/lib/fb-schedule.js"
      ],
      "kinds": [
        "fb-schedule-api"
      ]
    },
    {
      "path": "/api/fb/schedule/telegram-command",
      "sources": [
        "electron/lib/fb-schedule.js"
      ],
      "kinds": [
        "fb-schedule-api"
      ]
    },
    {
      "path": "/api/fb/schedule/trigger-generate",
      "sources": [
        "electron/lib/fb-schedule.js"
      ],
      "kinds": [
        "fb-schedule-api"
      ]
    },
    {
      "path": "/api/fb/schedule/update",
      "sources": [
        "electron/lib/fb-schedule.js"
      ],
      "kinds": [
        "fb-schedule-api"
      ]
    },
    {
      "path": "/api/fb/verify",
      "sources": [
        "electron/lib/cron-api.js"
      ],
      "kinds": [
        "local-api"
      ]
    },
    {
      "path": "/api/file",
      "sources": [
        "electron/lib/cron-api.js"
      ],
      "kinds": [
        "local-api"
      ]
    },
    {
      "path": "/api/file/copy",
      "sources": [
        "electron/lib/cron-api.js"
      ],
      "kinds": [
        "local-api"
      ]
    },
    {
      "path": "/api/file/delete",
      "sources": [
        "electron/lib/cron-api.js"
      ],
      "kinds": [
        "local-api"
      ]
    },
    {
      "path": "/api/file/download",
      "sources": [
        "electron/lib/cron-api.js"
      ],
      "kinds": [
        "local-api"
      ]
    },
    {
      "path": "/api/file/list",
      "sources": [
        "electron/lib/cron-api.js"
      ],
      "kinds": [
        "local-api"
      ]
    },
    {
      "path": "/api/file/open",
      "sources": [
        "electron/lib/cron-api.js"
      ],
      "kinds": [
        "local-api"
      ]
    },
    {
      "path": "/api/file/read",
      "sources": [
        "electron/lib/cron-api.js"
      ],
      "kinds": [
        "local-api"
      ]
    },
    {
      "path": "/api/file/rename",
      "sources": [
        "electron/lib/cron-api.js"
      ],
      "kinds": [
        "local-api"
      ]
    },
    {
      "path": "/api/file/search",
      "sources": [
        "electron/lib/cron-api.js"
      ],
      "kinds": [
        "local-api"
      ]
    },
    {
      "path": "/api/file/write",
      "sources": [
        "electron/lib/cron-api.js"
      ],
      "kinds": [
        "local-api"
      ]
    },
    {
      "path": "/api/google",
      "sources": [
        "electron/lib/cron-api.js"
      ],
      "kinds": [
        "local-api"
      ]
    },
    {
      "path": "/api/google/appscript/run",
      "sources": [
        "electron/lib/google-routes.js"
      ],
      "kinds": [
        "google-api"
      ]
    },
    {
      "path": "/api/google/calendar/create",
      "sources": [
        "electron/lib/google-routes.js"
      ],
      "kinds": [
        "google-api"
      ]
    },
    {
      "path": "/api/google/calendar/delete",
      "sources": [
        "electron/lib/google-routes.js"
      ],
      "kinds": [
        "google-api"
      ]
    },
    {
      "path": "/api/google/calendar/events",
      "sources": [
        "electron/lib/google-routes.js"
      ],
      "kinds": [
        "google-api"
      ]
    },
    {
      "path": "/api/google/calendar/free-slots",
      "sources": [
        "electron/lib/google-routes.js"
      ],
      "kinds": [
        "google-api"
      ]
    },
    {
      "path": "/api/google/calendar/freebusy",
      "sources": [
        "electron/lib/google-routes.js"
      ],
      "kinds": [
        "google-api"
      ]
    },
    {
      "path": "/api/google/calendar/update",
      "sources": [
        "electron/lib/google-routes.js"
      ],
      "kinds": [
        "google-api"
      ]
    },
    {
      "path": "/api/google/contacts/create",
      "sources": [
        "electron/lib/google-routes.js"
      ],
      "kinds": [
        "google-api"
      ]
    },
    {
      "path": "/api/google/contacts/list",
      "sources": [
        "electron/lib/google-routes.js"
      ],
      "kinds": [
        "google-api"
      ]
    },
    {
      "path": "/api/google/contacts/search",
      "sources": [
        "electron/lib/google-routes.js"
      ],
      "kinds": [
        "google-api"
      ]
    },
    {
      "path": "/api/google/docs/create",
      "sources": [
        "electron/lib/google-routes.js"
      ],
      "kinds": [
        "google-api"
      ]
    },
    {
      "path": "/api/google/docs/export",
      "sources": [
        "electron/lib/google-routes.js"
      ],
      "kinds": [
        "google-api"
      ]
    },
    {
      "path": "/api/google/docs/find-replace",
      "sources": [
        "electron/lib/google-routes.js"
      ],
      "kinds": [
        "google-api"
      ]
    },
    {
      "path": "/api/google/docs/info",
      "sources": [
        "electron/lib/google-routes.js"
      ],
      "kinds": [
        "google-api"
      ]
    },
    {
      "path": "/api/google/docs/insert",
      "sources": [
        "electron/lib/google-routes.js"
      ],
      "kinds": [
        "google-api"
      ]
    },
    {
      "path": "/api/google/docs/list",
      "sources": [
        "electron/lib/google-routes.js"
      ],
      "kinds": [
        "google-api"
      ]
    },
    {
      "path": "/api/google/docs/read",
      "sources": [
        "electron/lib/google-routes.js"
      ],
      "kinds": [
        "google-api"
      ]
    },
    {
      "path": "/api/google/docs/write",
      "sources": [
        "electron/lib/google-routes.js"
      ],
      "kinds": [
        "google-api"
      ]
    },
    {
      "path": "/api/google/drive/download",
      "sources": [
        "electron/lib/google-routes.js"
      ],
      "kinds": [
        "google-api"
      ]
    },
    {
      "path": "/api/google/drive/list",
      "sources": [
        "electron/lib/google-routes.js"
      ],
      "kinds": [
        "google-api"
      ]
    },
    {
      "path": "/api/google/drive/share",
      "sources": [
        "electron/lib/google-routes.js"
      ],
      "kinds": [
        "google-api"
      ]
    },
    {
      "path": "/api/google/drive/upload",
      "sources": [
        "electron/lib/google-routes.js"
      ],
      "kinds": [
        "google-api"
      ]
    },
    {
      "path": "/api/google/gmail/inbox",
      "sources": [
        "electron/lib/google-routes.js"
      ],
      "kinds": [
        "google-api"
      ]
    },
    {
      "path": "/api/google/gmail/read",
      "sources": [
        "electron/lib/google-routes.js"
      ],
      "kinds": [
        "google-api"
      ]
    },
    {
      "path": "/api/google/gmail/reply",
      "sources": [
        "electron/lib/google-routes.js"
      ],
      "kinds": [
        "google-api"
      ]
    },
    {
      "path": "/api/google/gmail/send",
      "sources": [
        "electron/lib/google-routes.js"
      ],
      "kinds": [
        "google-api"
      ]
    },
    {
      "path": "/api/google/health",
      "sources": [
        "electron/lib/google-routes.js"
      ],
      "kinds": [
        "google-api"
      ]
    },
    {
      "path": "/api/google/sheets/append",
      "sources": [
        "electron/lib/google-routes.js"
      ],
      "kinds": [
        "google-api"
      ]
    },
    {
      "path": "/api/google/sheets/get",
      "sources": [
        "electron/lib/google-routes.js"
      ],
      "kinds": [
        "google-api"
      ]
    },
    {
      "path": "/api/google/sheets/list",
      "sources": [
        "electron/lib/google-routes.js"
      ],
      "kinds": [
        "google-api"
      ]
    },
    {
      "path": "/api/google/sheets/metadata",
      "sources": [
        "electron/lib/google-routes.js"
      ],
      "kinds": [
        "google-api"
      ]
    },
    {
      "path": "/api/google/sheets/update",
      "sources": [
        "electron/lib/google-routes.js"
      ],
      "kinds": [
        "google-api"
      ]
    },
    {
      "path": "/api/google/status",
      "sources": [
        "electron/lib/google-routes.js"
      ],
      "kinds": [
        "google-api"
      ]
    },
    {
      "path": "/api/google/tasks/complete",
      "sources": [
        "electron/lib/google-routes.js"
      ],
      "kinds": [
        "google-api"
      ]
    },
    {
      "path": "/api/google/tasks/create",
      "sources": [
        "electron/lib/google-routes.js"
      ],
      "kinds": [
        "google-api"
      ]
    },
    {
      "path": "/api/google/tasks/list",
      "sources": [
        "electron/lib/google-routes.js"
      ],
      "kinds": [
        "google-api"
      ]
    },
    {
      "path": "/api/google/tasks/lists",
      "sources": [
        "electron/lib/google-routes.js"
      ],
      "kinds": [
        "google-api"
      ]
    },
    {
      "path": "/api/image/generate",
      "sources": [
        "electron/lib/cron-api.js"
      ],
      "kinds": [
        "local-api"
      ]
    },
    {
      "path": "/api/image/generate-and-send-zalo",
      "sources": [
        "electron/lib/cron-api.js"
      ],
      "kinds": [
        "local-api"
      ]
    },
    {
      "path": "/api/image/preferences",
      "sources": [
        "electron/lib/cron-api.js"
      ],
      "kinds": [
        "local-api"
      ]
    },
    {
      "path": "/api/image/skills",
      "sources": [
        "electron/lib/cron-api.js"
      ],
      "kinds": [
        "local-api"
      ]
    },
    {
      "path": "/api/image/status",
      "sources": [
        "electron/lib/cron-api.js"
      ],
      "kinds": [
        "local-api"
      ]
    },
    {
      "path": "/api/internal/agent-deliver-zalo",
      "sources": [
        "electron/lib/cron-api.js"
      ],
      "kinds": [
        "local-api"
      ]
    },
    {
      "path": "/api/knowledge/add",
      "sources": [
        "electron/lib/cron-api.js"
      ],
      "kinds": [
        "local-api"
      ]
    },
    {
      "path": "/api/media/describe",
      "sources": [
        "electron/lib/cron-api.js"
      ],
      "kinds": [
        "local-api"
      ]
    },
    {
      "path": "/api/media/list",
      "sources": [
        "electron/lib/cron-api.js"
      ],
      "kinds": [
        "local-api"
      ]
    },
    {
      "path": "/api/media/search",
      "sources": [
        "electron/lib/cron-api.js"
      ],
      "kinds": [
        "local-api"
      ]
    },
    {
      "path": "/api/media/upload",
      "sources": [
        "electron/lib/cron-api.js"
      ],
      "kinds": [
        "local-api"
      ]
    },
    {
      "path": "/api/memory/count",
      "sources": [
        "electron/lib/cron-api.js"
      ],
      "kinds": [
        "local-api"
      ]
    },
    {
      "path": "/api/memory/delete",
      "sources": [
        "electron/lib/cron-api.js"
      ],
      "kinds": [
        "local-api"
      ]
    },
    {
      "path": "/api/memory/list",
      "sources": [
        "electron/lib/cron-api.js"
      ],
      "kinds": [
        "local-api"
      ]
    },
    {
      "path": "/api/memory/search",
      "sources": [
        "electron/lib/cron-api.js"
      ],
      "kinds": [
        "local-api"
      ]
    },
    {
      "path": "/api/memory/write",
      "sources": [
        "electron/lib/cron-api.js"
      ],
      "kinds": [
        "local-api"
      ]
    },
    {
      "path": "/api/system/info",
      "sources": [
        "electron/lib/cron-api.js"
      ],
      "kinds": [
        "local-api"
      ]
    },
    {
      "path": "/api/telegram/send-photo",
      "sources": [
        "electron/lib/cron-api.js"
      ],
      "kinds": [
        "local-api"
      ]
    },
    {
      "path": "/api/workspace/append",
      "sources": [
        "electron/lib/cron-api.js"
      ],
      "kinds": [
        "local-api"
      ]
    },
    {
      "path": "/api/workspace/list",
      "sources": [
        "electron/lib/cron-api.js"
      ],
      "kinds": [
        "local-api"
      ]
    },
    {
      "path": "/api/workspace/read",
      "sources": [
        "electron/lib/cron-api.js"
      ],
      "kinds": [
        "local-api"
      ]
    },
    {
      "path": "/api/zalo/friends",
      "sources": [
        "electron/lib/cron-api.js"
      ],
      "kinds": [
        "local-api"
      ]
    },
    {
      "path": "/api/zalo/ready",
      "sources": [
        "electron/lib/cron-api.js"
      ],
      "kinds": [
        "local-api"
      ]
    },
    {
      "path": "/api/zalo/send",
      "sources": [
        "electron/lib/cron-api.js"
      ],
      "kinds": [
        "local-api"
      ]
    },
    {
      "path": "/api/zalo/send-media",
      "sources": [
        "electron/lib/cron-api.js"
      ],
      "kinds": [
        "local-api"
      ]
    }
  ],
  "ipcHandlers": [
    {
      "channel": "activate-license",
      "source": "electron/lib/dashboard-ipc.js"
    },
    {
      "channel": "add-cron",
      "source": "electron/lib/dashboard-ipc.js"
    },
    {
      "channel": "append-zalo-user-note",
      "source": "electron/lib/dashboard-ipc.js"
    },
    {
      "channel": "check-all-channels",
      "source": "electron/lib/dashboard-ipc.js"
    },
    {
      "channel": "check-for-updates",
      "source": "electron/lib/dashboard-ipc.js"
    },
    {
      "channel": "check-guide-needed",
      "source": "electron/lib/dashboard-ipc.js"
    },
    {
      "channel": "check-telegram-ready",
      "source": "electron/lib/dashboard-ipc.js"
    },
    {
      "channel": "check-zalo-login",
      "source": "electron/lib/dashboard-ipc.js"
    },
    {
      "channel": "check-zalo-ready",
      "source": "electron/lib/dashboard-ipc.js"
    },
    {
      "channel": "compact-all-sessions",
      "source": "electron/lib/dashboard-ipc.js"
    },
    {
      "channel": "compact-session",
      "source": "electron/lib/dashboard-ipc.js"
    },
    {
      "channel": "create-appointment",
      "source": "electron/lib/dashboard-ipc.js"
    },
    {
      "channel": "create-knowledge-folder",
      "source": "electron/lib/dashboard-ipc.js"
    },
    {
      "channel": "cron-diagnostic",
      "source": "electron/lib/dashboard-ipc.js"
    },
    {
      "channel": "deactivate-license",
      "source": "electron/lib/dashboard-ipc.js"
    },
    {
      "channel": "delete-appointment",
      "source": "electron/lib/dashboard-ipc.js"
    },
    {
      "channel": "delete-brand-asset",
      "source": "electron/lib/dashboard-ipc.js"
    },
    {
      "channel": "delete-ceo-memory",
      "source": "electron/lib/dashboard-ipc.js"
    },
    {
      "channel": "delete-document",
      "source": "electron/lib/dashboard-ipc.js"
    },
    {
      "channel": "delete-knowledge-file",
      "source": "electron/lib/dashboard-ipc.js"
    },
    {
      "channel": "delete-knowledge-folder",
      "source": "electron/lib/dashboard-ipc.js"
    },
    {
      "channel": "delete-media-asset",
      "source": "electron/lib/dashboard-ipc.js"
    },
    {
      "channel": "delete-openclaw-cron",
      "source": "electron/lib/dashboard-ipc.js"
    },
    {
      "channel": "delete-zalo-user-note",
      "source": "electron/lib/dashboard-ipc.js"
    },
    {
      "channel": "describe-media-asset",
      "source": "electron/lib/dashboard-ipc.js"
    },
    {
      "channel": "download-and-install-update",
      "source": "electron/lib/dashboard-ipc.js"
    },
    {
      "channel": "export-workspace",
      "source": "electron/lib/dashboard-ipc.js"
    },
    {
      "channel": "factory-reset",
      "source": "electron/lib/dashboard-ipc.js"
    },
    {
      "channel": "find-zalo-qr",
      "source": "electron/lib/dashboard-ipc.js"
    },
    {
      "channel": "get-app-prefs",
      "source": "electron/lib/dashboard-ipc.js"
    },
    {
      "channel": "get-app-version",
      "source": "electron/lib/dashboard-ipc.js"
    },
    {
      "channel": "get-bot-status",
      "source": "electron/lib/dashboard-ipc.js"
    },
    {
      "channel": "get-ceo-memories",
      "source": "electron/lib/dashboard-ipc.js"
    },
    {
      "channel": "get-ceo-memory-count",
      "source": "electron/lib/dashboard-ipc.js"
    },
    {
      "channel": "get-compact-stats",
      "source": "electron/lib/dashboard-ipc.js"
    },
    {
      "channel": "get-custom-crons",
      "source": "electron/lib/dashboard-ipc.js"
    },
    {
      "channel": "get-dashboard",
      "source": "electron/lib/dashboard-ipc.js"
    },
    {
      "channel": "get-diagnostic-log",
      "source": "electron/lib/dashboard-ipc.js"
    },
    {
      "channel": "get-fb-config",
      "source": "electron/lib/dashboard-ipc.js"
    },
    {
      "channel": "get-fb-recent-posts",
      "source": "electron/lib/dashboard-ipc.js"
    },
    {
      "channel": "get-gateway-token",
      "source": "electron/lib/dashboard-ipc.js"
    },
    {
      "channel": "get-inbound-debounce",
      "source": "electron/lib/dashboard-ipc.js"
    },
    {
      "channel": "get-knowledge-counts",
      "source": "electron/lib/dashboard-ipc.js"
    },
    {
      "channel": "get-license-status",
      "source": "electron/lib/dashboard-ipc.js"
    },
    {
      "channel": "get-overview-data",
      "source": "electron/lib/dashboard-ipc.js"
    },
    {
      "channel": "get-persona-mix",
      "source": "electron/lib/dashboard-ipc.js"
    },
    {
      "channel": "get-rag-config",
      "source": "electron/lib/dashboard-ipc.js"
    },
    {
      "channel": "get-schedules",
      "source": "electron/lib/dashboard-ipc.js"
    },
    {
      "channel": "get-shop-state",
      "source": "electron/lib/dashboard-ipc.js"
    },
    {
      "channel": "get-telegram-behavior",
      "source": "electron/lib/dashboard-ipc.js"
    },
    {
      "channel": "get-telegram-config",
      "source": "electron/lib/dashboard-ipc.js"
    },
    {
      "channel": "get-telegram-pause-status",
      "source": "electron/lib/dashboard-ipc.js"
    },
    {
      "channel": "get-zalo-group-memory",
      "source": "electron/lib/dashboard-ipc.js"
    },
    {
      "channel": "get-zalo-group-summaries",
      "source": "electron/lib/dashboard-ipc.js"
    },
    {
      "channel": "get-zalo-manager-config",
      "source": "electron/lib/dashboard-ipc.js"
    },
    {
      "channel": "get-zalo-mode",
      "source": "electron/lib/dashboard-ipc.js"
    },
    {
      "channel": "get-zalo-pause-status",
      "source": "electron/lib/dashboard-ipc.js"
    },
    {
      "channel": "google-appscript-run",
      "source": "electron/lib/dashboard-ipc.js"
    },
    {
      "channel": "google-auth-status",
      "source": "electron/lib/dashboard-ipc.js"
    },
    {
      "channel": "google-calendar-create",
      "source": "electron/lib/dashboard-ipc.js"
    },
    {
      "channel": "google-calendar-delete",
      "source": "electron/lib/dashboard-ipc.js"
    },
    {
      "channel": "google-calendar-events",
      "source": "electron/lib/dashboard-ipc.js"
    },
    {
      "channel": "google-calendar-free-slots",
      "source": "electron/lib/dashboard-ipc.js"
    },
    {
      "channel": "google-calendar-freebusy",
      "source": "electron/lib/dashboard-ipc.js"
    },
    {
      "channel": "google-calendar-update",
      "source": "electron/lib/dashboard-ipc.js"
    },
    {
      "channel": "google-connect",
      "source": "electron/lib/dashboard-ipc.js"
    },
    {
      "channel": "google-contacts-create",
      "source": "electron/lib/dashboard-ipc.js"
    },
    {
      "channel": "google-contacts-list",
      "source": "electron/lib/dashboard-ipc.js"
    },
    {
      "channel": "google-disconnect",
      "source": "electron/lib/dashboard-ipc.js"
    },
    {
      "channel": "google-docs-create",
      "source": "electron/lib/dashboard-ipc.js"
    },
    {
      "channel": "google-docs-export",
      "source": "electron/lib/dashboard-ipc.js"
    },
    {
      "channel": "google-docs-find-replace",
      "source": "electron/lib/dashboard-ipc.js"
    },
    {
      "channel": "google-docs-info",
      "source": "electron/lib/dashboard-ipc.js"
    },
    {
      "channel": "google-docs-insert",
      "source": "electron/lib/dashboard-ipc.js"
    },
    {
      "channel": "google-docs-list",
      "source": "electron/lib/dashboard-ipc.js"
    },
    {
      "channel": "google-docs-read",
      "source": "electron/lib/dashboard-ipc.js"
    },
    {
      "channel": "google-docs-write",
      "source": "electron/lib/dashboard-ipc.js"
    },
    {
      "channel": "google-drive-download",
      "source": "electron/lib/dashboard-ipc.js"
    },
    {
      "channel": "google-drive-list",
      "source": "electron/lib/dashboard-ipc.js"
    },
    {
      "channel": "google-drive-share",
      "source": "electron/lib/dashboard-ipc.js"
    },
    {
      "channel": "google-drive-upload",
      "source": "electron/lib/dashboard-ipc.js"
    },
    {
      "channel": "google-gmail-inbox",
      "source": "electron/lib/dashboard-ipc.js"
    },
    {
      "channel": "google-gmail-read",
      "source": "electron/lib/dashboard-ipc.js"
    },
    {
      "channel": "google-gmail-reply",
      "source": "electron/lib/dashboard-ipc.js"
    },
    {
      "channel": "google-gmail-send",
      "source": "electron/lib/dashboard-ipc.js"
    },
    {
      "channel": "google-health",
      "source": "electron/lib/dashboard-ipc.js"
    },
    {
      "channel": "google-sheets-append",
      "source": "electron/lib/dashboard-ipc.js"
    },
    {
      "channel": "google-sheets-get",
      "source": "electron/lib/dashboard-ipc.js"
    },
    {
      "channel": "google-sheets-list",
      "source": "electron/lib/dashboard-ipc.js"
    },
    {
      "channel": "google-sheets-metadata",
      "source": "electron/lib/dashboard-ipc.js"
    },
    {
      "channel": "google-sheets-update",
      "source": "electron/lib/dashboard-ipc.js"
    },
    {
      "channel": "google-tasks-complete",
      "source": "electron/lib/dashboard-ipc.js"
    },
    {
      "channel": "google-tasks-create",
      "source": "electron/lib/dashboard-ipc.js"
    },
    {
      "channel": "google-tasks-list",
      "source": "electron/lib/dashboard-ipc.js"
    },
    {
      "channel": "google-tasks-lists",
      "source": "electron/lib/dashboard-ipc.js"
    },
    {
      "channel": "google-upload-credentials",
      "source": "electron/lib/dashboard-ipc.js"
    },
    {
      "channel": "import-workspace",
      "source": "electron/lib/dashboard-ipc.js"
    },
    {
      "channel": "index-document",
      "source": "electron/lib/dashboard-ipc.js"
    },
    {
      "channel": "install-openclaw",
      "source": "electron/lib/dashboard-ipc.js"
    },
    {
      "channel": "knowledge-search",
      "source": "electron/lib/dashboard-ipc.js"
    },
    {
      "channel": "list-appointments",
      "source": "electron/lib/dashboard-ipc.js"
    },
    {
      "channel": "list-brand-assets",
      "source": "electron/lib/dashboard-ipc.js"
    },
    {
      "channel": "list-documents",
      "source": "electron/lib/dashboard-ipc.js"
    },
    {
      "channel": "list-knowledge-files",
      "source": "electron/lib/dashboard-ipc.js"
    },
    {
      "channel": "list-knowledge-folders",
      "source": "electron/lib/dashboard-ipc.js"
    },
    {
      "channel": "list-media-assets",
      "source": "electron/lib/dashboard-ipc.js"
    },
    {
      "channel": "list-zalo-friends",
      "source": "electron/lib/dashboard-ipc.js"
    },
    {
      "channel": "list-zalo-groups",
      "source": "electron/lib/dashboard-ipc.js"
    },
    {
      "channel": "list-zalo-user-memories",
      "source": "electron/lib/dashboard-ipc.js"
    },
    {
      "channel": "mark-guide-complete",
      "source": "electron/lib/dashboard-ipc.js"
    },
    {
      "channel": "open-external",
      "source": "electron/lib/dashboard-ipc.js"
    },
    {
      "channel": "open-log-folder",
      "source": "electron/lib/dashboard-ipc.js"
    },
    {
      "channel": "pause-telegram",
      "source": "electron/lib/dashboard-ipc.js"
    },
    {
      "channel": "pause-zalo",
      "source": "electron/lib/dashboard-ipc.js"
    },
    {
      "channel": "pick-brand-asset-file",
      "source": "electron/lib/dashboard-ipc.js"
    },
    {
      "channel": "pick-knowledge-file",
      "source": "electron/lib/dashboard-ipc.js"
    },
    {
      "channel": "pick-media-asset-file",
      "source": "electron/lib/dashboard-ipc.js"
    },
    {
      "channel": "queue-follow-up",
      "source": "electron/lib/dashboard-ipc.js"
    },
    {
      "channel": "read-zalo-user-memory",
      "source": "electron/lib/dashboard-ipc.js"
    },
    {
      "channel": "refresh-zalo-cache",
      "source": "electron/lib/dashboard-ipc.js"
    },
    {
      "channel": "relaunch",
      "source": "electron/lib/dashboard-ipc.js"
    },
    {
      "channel": "reset-zalo-user-memory",
      "source": "electron/lib/dashboard-ipc.js"
    },
    {
      "channel": "resolve-zalo-target",
      "source": "electron/lib/dashboard-ipc.js"
    },
    {
      "channel": "resume-telegram",
      "source": "electron/lib/dashboard-ipc.js"
    },
    {
      "channel": "resume-zalo",
      "source": "electron/lib/dashboard-ipc.js"
    },
    {
      "channel": "save-business-profile",
      "source": "electron/lib/dashboard-ipc.js"
    },
    {
      "channel": "save-custom-crons",
      "source": "electron/lib/dashboard-ipc.js"
    },
    {
      "channel": "save-fb-config",
      "source": "electron/lib/dashboard-ipc.js"
    },
    {
      "channel": "save-persona-mix",
      "source": "electron/lib/dashboard-ipc.js"
    },
    {
      "channel": "save-personalization",
      "source": "electron/lib/dashboard-ipc.js"
    },
    {
      "channel": "save-schedules",
      "source": "electron/lib/dashboard-ipc.js"
    },
    {
      "channel": "save-telegram-behavior",
      "source": "electron/lib/dashboard-ipc.js"
    },
    {
      "channel": "save-telegram-config",
      "source": "electron/lib/dashboard-ipc.js"
    },
    {
      "channel": "save-wizard-config",
      "source": "electron/lib/dashboard-ipc.js"
    },
    {
      "channel": "save-zalo-manager-config",
      "source": "electron/lib/dashboard-ipc.js"
    },
    {
      "channel": "save-zalo-mode",
      "source": "electron/lib/dashboard-ipc.js"
    },
    {
      "channel": "search-ceo-memories",
      "source": "electron/lib/dashboard-ipc.js"
    },
    {
      "channel": "search-documents",
      "source": "electron/lib/dashboard-ipc.js"
    },
    {
      "channel": "seed-group-history-all",
      "source": "electron/lib/dashboard-ipc.js"
    },
    {
      "channel": "seed-group-history-now",
      "source": "electron/lib/dashboard-ipc.js"
    },
    {
      "channel": "set-app-prefs",
      "source": "electron/lib/dashboard-ipc.js"
    },
    {
      "channel": "set-batch-config",
      "source": "electron/lib/dashboard-ipc.js"
    },
    {
      "channel": "set-inbound-debounce",
      "source": "electron/lib/dashboard-ipc.js"
    },
    {
      "channel": "set-knowledge-visibility",
      "source": "electron/lib/dashboard-ipc.js"
    },
    {
      "channel": "set-rag-config",
      "source": "electron/lib/dashboard-ipc.js"
    },
    {
      "channel": "set-shop-state",
      "source": "electron/lib/dashboard-ipc.js"
    },
    {
      "channel": "setup-9router-auto",
      "source": "electron/lib/dashboard-ipc.js"
    },
    {
      "channel": "setup-zalo",
      "source": "electron/lib/dashboard-ipc.js"
    },
    {
      "channel": "start-9router",
      "source": "electron/lib/dashboard-ipc.js"
    },
    {
      "channel": "telegram-self-test",
      "source": "electron/lib/dashboard-ipc.js"
    },
    {
      "channel": "test-cron",
      "source": "electron/lib/dashboard-ipc.js"
    },
    {
      "channel": "test-telegram",
      "source": "electron/lib/dashboard-ipc.js"
    },
    {
      "channel": "toggle-bot",
      "source": "electron/lib/dashboard-ipc.js"
    },
    {
      "channel": "update-appointment",
      "source": "electron/lib/dashboard-ipc.js"
    },
    {
      "channel": "upload-brand-asset",
      "source": "electron/lib/dashboard-ipc.js"
    },
    {
      "channel": "upload-knowledge-file",
      "source": "electron/lib/dashboard-ipc.js"
    },
    {
      "channel": "upload-media-asset",
      "source": "electron/lib/dashboard-ipc.js"
    },
    {
      "channel": "verify-fb-token",
      "source": "electron/lib/dashboard-ipc.js"
    },
    {
      "channel": "wizard-complete",
      "source": "electron/lib/dashboard-ipc.js"
    },
    {
      "channel": "write-ceo-memory",
      "source": "electron/lib/dashboard-ipc.js"
    }
  ],
  "preloadBridges": [
    {
      "name": "activateLicense",
      "channel": "activate-license",
      "source": "electron/preload.js"
    },
    {
      "name": "addCron",
      "channel": "add-cron",
      "source": "electron/preload.js"
    },
    {
      "name": "appendZaloUserNote",
      "channel": "append-zalo-user-note",
      "source": "electron/preload.js"
    },
    {
      "name": "checkAllChannels",
      "channel": "check-all-channels",
      "source": "electron/preload.js"
    },
    {
      "name": "checkForUpdates",
      "channel": "check-for-updates",
      "source": "electron/preload.js"
    },
    {
      "name": "checkGuideNeeded",
      "channel": "check-guide-needed",
      "source": "electron/preload.js"
    },
    {
      "name": "checkTelegramReady",
      "channel": "check-telegram-ready",
      "source": "electron/preload.js"
    },
    {
      "name": "checkZaloLogin",
      "channel": "check-zalo-login",
      "source": "electron/preload.js"
    },
    {
      "name": "checkZaloReady",
      "channel": "check-zalo-ready",
      "source": "electron/preload.js"
    },
    {
      "name": "createAppointment",
      "channel": "create-appointment",
      "source": "electron/preload.js"
    },
    {
      "name": "createKnowledgeFolder",
      "channel": "create-knowledge-folder",
      "source": "electron/preload.js"
    },
    {
      "name": "deactivateLicense",
      "channel": "deactivate-license",
      "source": "electron/preload.js"
    },
    {
      "name": "deleteAppointment",
      "channel": "delete-appointment",
      "source": "electron/preload.js"
    },
    {
      "name": "deleteBrandAsset",
      "channel": "delete-brand-asset",
      "source": "electron/preload.js"
    },
    {
      "name": "deleteCeoMemory",
      "channel": "delete-ceo-memory",
      "source": "electron/preload.js"
    },
    {
      "name": "deleteDocument",
      "channel": "delete-document",
      "source": "electron/preload.js"
    },
    {
      "name": "deleteKnowledgeFile",
      "channel": "delete-knowledge-file",
      "source": "electron/preload.js"
    },
    {
      "name": "deleteKnowledgeFolder",
      "channel": "delete-knowledge-folder",
      "source": "electron/preload.js"
    },
    {
      "name": "deleteMediaAsset",
      "channel": "delete-media-asset",
      "source": "electron/preload.js"
    },
    {
      "name": "deleteOpenclawCron",
      "channel": "delete-openclaw-cron",
      "source": "electron/preload.js"
    },
    {
      "name": "deleteZaloUserNote",
      "channel": "delete-zalo-user-note",
      "source": "electron/preload.js"
    },
    {
      "name": "describeMediaAsset",
      "channel": "describe-media-asset",
      "source": "electron/preload.js"
    },
    {
      "name": "downloadAndInstallUpdate",
      "channel": "download-and-install-update",
      "source": "electron/preload.js"
    },
    {
      "name": "exportWorkspace",
      "channel": "export-workspace",
      "source": "electron/preload.js"
    },
    {
      "name": "factoryReset",
      "channel": "factory-reset",
      "source": "electron/preload.js"
    },
    {
      "name": "findZaloQR",
      "channel": "find-zalo-qr",
      "source": "electron/preload.js"
    },
    {
      "name": "getAppPrefs",
      "channel": "get-app-prefs",
      "source": "electron/preload.js"
    },
    {
      "name": "getAppVersion",
      "channel": "get-app-version",
      "source": "electron/preload.js"
    },
    {
      "name": "getBotStatus",
      "channel": "get-bot-status",
      "source": "electron/preload.js"
    },
    {
      "name": "getCeoMemories",
      "channel": "get-ceo-memories",
      "source": "electron/preload.js"
    },
    {
      "name": "getCeoMemoryCount",
      "channel": "get-ceo-memory-count",
      "source": "electron/preload.js"
    },
    {
      "name": "getCustomCrons",
      "channel": "get-custom-crons",
      "source": "electron/preload.js"
    },
    {
      "name": "getDashboard",
      "channel": "get-dashboard",
      "source": "electron/preload.js"
    },
    {
      "name": "getDiagnosticLog",
      "channel": "get-diagnostic-log",
      "source": "electron/preload.js"
    },
    {
      "name": "getFbConfig",
      "channel": "get-fb-config",
      "source": "electron/preload.js"
    },
    {
      "name": "getFbRecentPosts",
      "channel": "get-fb-recent-posts",
      "source": "electron/preload.js"
    },
    {
      "name": "getGatewayToken",
      "channel": "get-gateway-token",
      "source": "electron/preload.js"
    },
    {
      "name": "getInboundDebounce",
      "channel": "get-inbound-debounce",
      "source": "electron/preload.js"
    },
    {
      "name": "getKnowledgeCounts",
      "channel": "get-knowledge-counts",
      "source": "electron/preload.js"
    },
    {
      "name": "getLicenseStatus",
      "channel": "get-license-status",
      "source": "electron/preload.js"
    },
    {
      "name": "getOverviewData",
      "channel": "get-overview-data",
      "source": "electron/preload.js"
    },
    {
      "name": "getPersonaMix",
      "channel": "get-persona-mix",
      "source": "electron/preload.js"
    },
    {
      "name": "getRagConfig",
      "channel": "get-rag-config",
      "source": "electron/preload.js"
    },
    {
      "name": "getSchedules",
      "channel": "get-schedules",
      "source": "electron/preload.js"
    },
    {
      "name": "getShopState",
      "channel": "get-shop-state",
      "source": "electron/preload.js"
    },
    {
      "name": "getTelegramBehavior",
      "channel": "get-telegram-behavior",
      "source": "electron/preload.js"
    },
    {
      "name": "getTelegramConfig",
      "channel": "get-telegram-config",
      "source": "electron/preload.js"
    },
    {
      "name": "getTelegramPauseStatus",
      "channel": "get-telegram-pause-status",
      "source": "electron/preload.js"
    },
    {
      "name": "getZaloGroupMemory",
      "channel": "get-zalo-group-memory",
      "source": "electron/preload.js"
    },
    {
      "name": "getZaloGroupSummaries",
      "channel": "get-zalo-group-summaries",
      "source": "electron/preload.js"
    },
    {
      "name": "getZaloManagerConfig",
      "channel": "get-zalo-manager-config",
      "source": "electron/preload.js"
    },
    {
      "name": "getZaloMode",
      "channel": "get-zalo-mode",
      "source": "electron/preload.js"
    },
    {
      "name": "getZaloPauseStatus",
      "channel": "get-zalo-pause-status",
      "source": "electron/preload.js"
    },
    {
      "name": "googleAppScriptRun",
      "channel": "google-appscript-run",
      "source": "electron/preload.js"
    },
    {
      "name": "googleAuthStatus",
      "channel": "google-auth-status",
      "source": "electron/preload.js"
    },
    {
      "name": "googleCalendarCreate",
      "channel": "google-calendar-create",
      "source": "electron/preload.js"
    },
    {
      "name": "googleCalendarDelete",
      "channel": "google-calendar-delete",
      "source": "electron/preload.js"
    },
    {
      "name": "googleCalendarEvents",
      "channel": "google-calendar-events",
      "source": "electron/preload.js"
    },
    {
      "name": "googleCalendarFreebusy",
      "channel": "google-calendar-freebusy",
      "source": "electron/preload.js"
    },
    {
      "name": "googleCalendarFreeSlots",
      "channel": "google-calendar-free-slots",
      "source": "electron/preload.js"
    },
    {
      "name": "googleCalendarUpdate",
      "channel": "google-calendar-update",
      "source": "electron/preload.js"
    },
    {
      "name": "googleConnect",
      "channel": "google-connect",
      "source": "electron/preload.js"
    },
    {
      "name": "googleContactsCreate",
      "channel": "google-contacts-create",
      "source": "electron/preload.js"
    },
    {
      "name": "googleContactsList",
      "channel": "google-contacts-list",
      "source": "electron/preload.js"
    },
    {
      "name": "googleDisconnect",
      "channel": "google-disconnect",
      "source": "electron/preload.js"
    },
    {
      "name": "googleDocsCreate",
      "channel": "google-docs-create",
      "source": "electron/preload.js"
    },
    {
      "name": "googleDocsExport",
      "channel": "google-docs-export",
      "source": "electron/preload.js"
    },
    {
      "name": "googleDocsFindReplace",
      "channel": "google-docs-find-replace",
      "source": "electron/preload.js"
    },
    {
      "name": "googleDocsInfo",
      "channel": "google-docs-info",
      "source": "electron/preload.js"
    },
    {
      "name": "googleDocsInsert",
      "channel": "google-docs-insert",
      "source": "electron/preload.js"
    },
    {
      "name": "googleDocsList",
      "channel": "google-docs-list",
      "source": "electron/preload.js"
    },
    {
      "name": "googleDocsRead",
      "channel": "google-docs-read",
      "source": "electron/preload.js"
    },
    {
      "name": "googleDocsWrite",
      "channel": "google-docs-write",
      "source": "electron/preload.js"
    },
    {
      "name": "googleDriveDownload",
      "channel": "google-drive-download",
      "source": "electron/preload.js"
    },
    {
      "name": "googleDriveList",
      "channel": "google-drive-list",
      "source": "electron/preload.js"
    },
    {
      "name": "googleDriveShare",
      "channel": "google-drive-share",
      "source": "electron/preload.js"
    },
    {
      "name": "googleDriveUpload",
      "channel": "google-drive-upload",
      "source": "electron/preload.js"
    },
    {
      "name": "googleGmailInbox",
      "channel": "google-gmail-inbox",
      "source": "electron/preload.js"
    },
    {
      "name": "googleGmailRead",
      "channel": "google-gmail-read",
      "source": "electron/preload.js"
    },
    {
      "name": "googleGmailReply",
      "channel": "google-gmail-reply",
      "source": "electron/preload.js"
    },
    {
      "name": "googleGmailSend",
      "channel": "google-gmail-send",
      "source": "electron/preload.js"
    },
    {
      "name": "googleHealth",
      "channel": "google-health",
      "source": "electron/preload.js"
    },
    {
      "name": "googleSheetsAppend",
      "channel": "google-sheets-append",
      "source": "electron/preload.js"
    },
    {
      "name": "googleSheetsGet",
      "channel": "google-sheets-get",
      "source": "electron/preload.js"
    },
    {
      "name": "googleSheetsList",
      "channel": "google-sheets-list",
      "source": "electron/preload.js"
    },
    {
      "name": "googleSheetsMetadata",
      "channel": "google-sheets-metadata",
      "source": "electron/preload.js"
    },
    {
      "name": "googleSheetsUpdate",
      "channel": "google-sheets-update",
      "source": "electron/preload.js"
    },
    {
      "name": "googleTaskLists",
      "channel": "google-tasks-lists",
      "source": "electron/preload.js"
    },
    {
      "name": "googleTasksComplete",
      "channel": "google-tasks-complete",
      "source": "electron/preload.js"
    },
    {
      "name": "googleTasksCreate",
      "channel": "google-tasks-create",
      "source": "electron/preload.js"
    },
    {
      "name": "googleTasksList",
      "channel": "google-tasks-list",
      "source": "electron/preload.js"
    },
    {
      "name": "googleUploadCredentials",
      "channel": "google-upload-credentials",
      "source": "electron/preload.js"
    },
    {
      "name": "importWorkspace",
      "channel": "import-workspace",
      "source": "electron/preload.js"
    },
    {
      "name": "indexDocument",
      "channel": "index-document",
      "source": "electron/preload.js"
    },
    {
      "name": "knowledgeSearch",
      "channel": "knowledge-search",
      "source": "electron/preload.js"
    },
    {
      "name": "listAppointments",
      "channel": "list-appointments",
      "source": "electron/preload.js"
    },
    {
      "name": "listBrandAssets",
      "channel": "list-brand-assets",
      "source": "electron/preload.js"
    },
    {
      "name": "listDocuments",
      "channel": "list-documents",
      "source": "electron/preload.js"
    },
    {
      "name": "listKnowledgeFiles",
      "channel": "list-knowledge-files",
      "source": "electron/preload.js"
    },
    {
      "name": "listKnowledgeFolders",
      "channel": "list-knowledge-folders",
      "source": "electron/preload.js"
    },
    {
      "name": "listMediaAssets",
      "channel": "list-media-assets",
      "source": "electron/preload.js"
    },
    {
      "name": "listZaloFriends",
      "channel": "list-zalo-friends",
      "source": "electron/preload.js"
    },
    {
      "name": "listZaloGroups",
      "channel": "list-zalo-groups",
      "source": "electron/preload.js"
    },
    {
      "name": "listZaloUserMemories",
      "channel": "list-zalo-user-memories",
      "source": "electron/preload.js"
    },
    {
      "name": "markGuideComplete",
      "channel": "mark-guide-complete",
      "source": "electron/preload.js"
    },
    {
      "name": "openExternal",
      "channel": "open-external",
      "source": "electron/preload.js"
    },
    {
      "name": "openLogFolder",
      "channel": "open-log-folder",
      "source": "electron/preload.js"
    },
    {
      "name": "pauseTelegram",
      "channel": "pause-telegram",
      "source": "electron/preload.js"
    },
    {
      "name": "pauseZalo",
      "channel": "pause-zalo",
      "source": "electron/preload.js"
    },
    {
      "name": "pickBrandAssetFile",
      "channel": "pick-brand-asset-file",
      "source": "electron/preload.js"
    },
    {
      "name": "pickKnowledgeFile",
      "channel": "pick-knowledge-file",
      "source": "electron/preload.js"
    },
    {
      "name": "pickMediaAssetFile",
      "channel": "pick-media-asset-file",
      "source": "electron/preload.js"
    },
    {
      "name": "readZaloUserMemory",
      "channel": "read-zalo-user-memory",
      "source": "electron/preload.js"
    },
    {
      "name": "refreshZaloCache",
      "channel": "refresh-zalo-cache",
      "source": "electron/preload.js"
    },
    {
      "name": "relaunch",
      "channel": "relaunch",
      "source": "electron/preload.js"
    },
    {
      "name": "resetZaloUserMemory",
      "channel": "reset-zalo-user-memory",
      "source": "electron/preload.js"
    },
    {
      "name": "resolveZaloTarget",
      "channel": "resolve-zalo-target",
      "source": "electron/preload.js"
    },
    {
      "name": "resumeTelegram",
      "channel": "resume-telegram",
      "source": "electron/preload.js"
    },
    {
      "name": "resumeZalo",
      "channel": "resume-zalo",
      "source": "electron/preload.js"
    },
    {
      "name": "saveBusinessProfile",
      "channel": "save-business-profile",
      "source": "electron/preload.js"
    },
    {
      "name": "saveCustomCrons",
      "channel": "save-custom-crons",
      "source": "electron/preload.js"
    },
    {
      "name": "saveFbConfig",
      "channel": "save-fb-config",
      "source": "electron/preload.js"
    },
    {
      "name": "savePersonalization",
      "channel": "save-personalization",
      "source": "electron/preload.js"
    },
    {
      "name": "savePersonaMix",
      "channel": "save-persona-mix",
      "source": "electron/preload.js"
    },
    {
      "name": "saveSchedules",
      "channel": "save-schedules",
      "source": "electron/preload.js"
    },
    {
      "name": "saveTelegramBehavior",
      "channel": "save-telegram-behavior",
      "source": "electron/preload.js"
    },
    {
      "name": "saveTelegramConfig",
      "channel": "save-telegram-config",
      "source": "electron/preload.js"
    },
    {
      "name": "saveWizardConfig",
      "channel": "save-wizard-config",
      "source": "electron/preload.js"
    },
    {
      "name": "saveZaloManagerConfig",
      "channel": "save-zalo-manager-config",
      "source": "electron/preload.js"
    },
    {
      "name": "saveZaloMode",
      "channel": "save-zalo-mode",
      "source": "electron/preload.js"
    },
    {
      "name": "searchCeoMemories",
      "channel": "search-ceo-memories",
      "source": "electron/preload.js"
    },
    {
      "name": "searchDocuments",
      "channel": "search-documents",
      "source": "electron/preload.js"
    },
    {
      "name": "setAppPrefs",
      "channel": "set-app-prefs",
      "source": "electron/preload.js"
    },
    {
      "name": "setBatchConfig",
      "channel": "set-batch-config",
      "source": "electron/preload.js"
    },
    {
      "name": "setInboundDebounce",
      "channel": "set-inbound-debounce",
      "source": "electron/preload.js"
    },
    {
      "name": "setKnowledgeVisibility",
      "channel": "set-knowledge-visibility",
      "source": "electron/preload.js"
    },
    {
      "name": "setRagConfig",
      "channel": "set-rag-config",
      "source": "electron/preload.js"
    },
    {
      "name": "setShopState",
      "channel": "set-shop-state",
      "source": "electron/preload.js"
    },
    {
      "name": "setup9RouterAuto",
      "channel": "setup-9router-auto",
      "source": "electron/preload.js"
    },
    {
      "name": "setupZalo",
      "channel": "setup-zalo",
      "source": "electron/preload.js"
    },
    {
      "name": "start9Router",
      "channel": "start-9router",
      "source": "electron/preload.js"
    },
    {
      "name": "telegramSelfTest",
      "channel": "telegram-self-test",
      "source": "electron/preload.js"
    },
    {
      "name": "testCron",
      "channel": "test-cron",
      "source": "electron/preload.js"
    },
    {
      "name": "testTelegram",
      "channel": "test-telegram",
      "source": "electron/preload.js"
    },
    {
      "name": "toggleBot",
      "channel": "toggle-bot",
      "source": "electron/preload.js"
    },
    {
      "name": "updateAppointment",
      "channel": "update-appointment",
      "source": "electron/preload.js"
    },
    {
      "name": "uploadBrandAsset",
      "channel": "upload-brand-asset",
      "source": "electron/preload.js"
    },
    {
      "name": "uploadKnowledgeFile",
      "channel": "upload-knowledge-file",
      "source": "electron/preload.js"
    },
    {
      "name": "uploadMediaAsset",
      "channel": "upload-media-asset",
      "source": "electron/preload.js"
    },
    {
      "name": "verifyFbToken",
      "channel": "verify-fb-token",
      "source": "electron/preload.js"
    },
    {
      "name": "wizardComplete",
      "channel": "wizard-complete",
      "source": "electron/preload.js"
    },
    {
      "name": "writeCeoMemory",
      "channel": "write-ceo-memory",
      "source": "electron/preload.js"
    }
  ],
  "dashboardPages": [
    {
      "id": "9router",
      "source": "electron/ui/dashboard.html"
    },
    {
      "id": "calendar",
      "source": "electron/ui/dashboard.html"
    },
    {
      "id": "chat",
      "source": "electron/ui/dashboard.html"
    },
    {
      "id": "facebook",
      "source": "electron/ui/dashboard.html"
    },
    {
      "id": "google",
      "source": "electron/ui/dashboard.html"
    },
    {
      "id": "image-assets",
      "source": "electron/ui/dashboard.html"
    },
    {
      "id": "knowledge",
      "source": "electron/ui/dashboard.html"
    },
    {
      "id": "openclaw",
      "source": "electron/ui/dashboard.html"
    },
    {
      "id": "overview",
      "source": "electron/ui/dashboard.html"
    },
    {
      "id": "persona-mix",
      "source": "electron/ui/dashboard.html"
    },
    {
      "id": "schedules",
      "source": "electron/ui/dashboard.html"
    },
    {
      "id": "shop-state",
      "source": "electron/ui/dashboard.html"
    },
    {
      "id": "telegram",
      "source": "electron/ui/dashboard.html"
    },
    {
      "id": "zalo",
      "source": "electron/ui/dashboard.html"
    }
  ],
  "capabilityContracts": [
    {
      "id": "brand-image",
      "title": "Generate brand-aware images with uploaded assets",
      "source": "capabilities/brand-image.contract.json"
    },
    {
      "id": "facebook-post",
      "title": "Publish to Facebook Fanpage",
      "source": "capabilities/facebook-post.contract.json"
    },
    {
      "id": "google-gmail",
      "title": "Read and send Gmail through connected Workspace",
      "source": "capabilities/google-gmail.contract.json"
    },
    {
      "id": "google-sheets",
      "title": "Read and update Google Sheets through connected Workspace",
      "source": "capabilities/google-sheets.contract.json"
    },
    {
      "id": "zalo-cron",
      "title": "Create scheduled Zalo group messages or agent jobs",
      "source": "capabilities/zalo-cron.contract.json"
    }
  ],
  "largeSourceFiles": [
    {
      "path": "electron/ui/dashboard.html",
      "bytes": 524791
    },
    {
      "path": "electron/lib/dashboard-ipc.js",
      "bytes": 230933
    },
    {
      "path": "electron/lib/cron-api.js",
      "bytes": 112191
    },
    {
      "path": "electron/lib/cron.js",
      "bytes": 100692
    },
    {
      "path": "electron/ui/wizard.html",
      "bytes": 87052
    },
    {
      "path": "electron/lib/channels.js",
      "bytes": 84587
    },
    {
      "path": "electron/lib/knowledge.js",
      "bytes": 77313
    },
    {
      "path": "electron/lib/runtime-installer.js",
      "bytes": 73846
    },
    {
      "path": "electron/lib/gateway.js",
      "bytes": 70353
    },
    {
      "path": "electron/lib/workspace.js",
      "bytes": 45923
    },
    {
      "path": "electron/lib/config.js",
      "bytes": 45718
    },
    {
      "path": "electron/lib/fb-schedule.js",
      "bytes": 39478
    },
    {
      "path": "electron/lib/nine-router.js",
      "bytes": 38508
    },
    {
      "path": "electron/lib/zalo-plugin.js",
      "bytes": 35090
    },
    {
      "path": "electron/lib/boot.js",
      "bytes": 35084
    },
    {
      "path": "electron/lib/vendor-patches.js",
      "bytes": 33786
    },
    {
      "path": "electron/lib/media-library.js",
      "bytes": 30376
    },
    {
      "path": "electron/lib/google-api.js",
      "bytes": 29327
    },
    {
      "path": "electron/lib/conversation.js",
      "bytes": 25838
    },
    {
      "path": "electron/ui/splash.html",
      "bytes": 24709
    }
  ]
}
